stactools/met_office_deterministic/__init__.py
stactools/met_office_deterministic/constants.py
stactools/met_office_deterministic/href.py
stactools/met_office_deterministic/stac.py
stactools/met_office_deterministic/item_assets/__init__.py
stactools/met_office_deterministic/item_assets/global-height.json
stactools/met_office_deterministic/item_assets/global-near-surface.json
stactools/met_office_deterministic/item_assets/global-pressure.json
stactools/met_office_deterministic/item_assets/global-whole-atmosphere.json
stactools/met_office_deterministic/item_assets/uk-height.json
stactools/met_office_deterministic/item_assets/uk-near-surface.json
stactools/met_office_deterministic/item_assets/uk-pressure.json
stactools/met_office_deterministic/item_assets/uk-whole-atmosphere.json
stactools_met_office_deterministic-0.4.0.dist-info/METADATA
stactools_met_office_deterministic-0.4.0.dist-info/WHEEL
stactools_met_office_deterministic-0.4.0.dist-info/licenses/LICENSE
stactools_met_office_deterministic-0.4.0.dist-info/RECORD
