Metadata-Version: 2.4
Name: stactools-met-office-deterministic
Version: 0.4.0
Summary: Python package for generating STAC metadata for the Met Office Deterministic Numerical Weather Prediction model
Author-email: Henry Rodman <henry@developmentseed.org>, Pete Gadomski <pete.gadomski@gmail.com>
License: MIT
License-File: LICENSE
Keywords: STAC,catalog,pystac,stactools
Classifier: Development Status :: 3 - Alpha
Classifier: Intended Audience :: Developers
Classifier: License :: OSI Approved :: Apache Software License
Classifier: Natural Language :: English
Classifier: Programming Language :: Python :: 3
Classifier: Programming Language :: Python :: 3.11
Classifier: Programming Language :: Python :: 3.12
Classifier: Programming Language :: Python :: 3.13
Classifier: Programming Language :: Python :: 3.14
Requires-Python: >=3.11
Requires-Dist: pystac>=1.10.1
Requires-Dist: shapely>=2.1.2
